pdf_cleanup_empty/__init__.py
pdf_cleanup_empty/cli.py
pdf_cleanup_empty/__pycache__/__init__.cpython-38.pyc
pdf_cleanup_empty/__pycache__/cli.cpython-38.pyc
pdf_cleanup_empty-0.0.1.dist-info/LICENSE
pdf_cleanup_empty-0.0.1.dist-info/METADATA
pdf_cleanup_empty-0.0.1.dist-info/WHEEL
pdf_cleanup_empty-0.0.1.dist-info/entry_points.txt
pdf_cleanup_empty-0.0.1.dist-info/top_level.txt
pdf_cleanup_empty-0.0.1.dist-info/RECORD
