Metadata-Version: 2.1
Name: pdf-cleanup-empty
Version: 0.0.1
Summary: This package can be used to remove white/empty pages from a pdf.
Author-email: Patrick Schleiter <git.pschleiter@gmail.com>
Project-URL: repository, https://github.com/pschleiter/pdf-cleanup-empty
Classifier: Development Status :: 3 - Alpha
Classifier: Intended Audience :: Developers
Classifier: License :: OSI Approved :: MIT License
Classifier: Operating System :: OS Independent
Classifier: Programming Language :: Python
Classifier: Programming Language :: Python :: 3
Classifier: Programming Language :: Python :: 3.8
Classifier: Programming Language :: Python :: 3.9
Classifier: Programming Language :: Python :: 3.10
Requires-Python: >=3.8
License-File: LICENSE
Requires-Dist: pikepdf
Requires-Dist: numpy
Requires-Dist: click
